README.txt
setup.cfg
setup.py
anz/__init__.py
anz.ijabbar.egg-info/PKG-INFO
anz.ijabbar.egg-info/SOURCES.txt
anz.ijabbar.egg-info/dependency_links.txt
anz.ijabbar.egg-info/entry_points.txt
anz.ijabbar.egg-info/namespace_packages.txt
anz.ijabbar.egg-info/not-zip-safe
anz.ijabbar.egg-info/paster_plugins.txt
anz.ijabbar.egg-info/requires.txt
anz.ijabbar.egg-info/top_level.txt
anz/ijabbar/__init__.py
anz/ijabbar/configure.zcml
anz/ijabbar/browser/__init__.py
anz/ijabbar/browser/configure.zcml
anz/ijabbar/browser/ijab_bar.pt
anz/ijabbar/browser/viewlets.py
anz/ijabbar/profiles/default/propertiestool.xml
anz/ijabbar/profiles/default/skins.xml
anz/ijabbar/skins/anz_ijabbar/Changes
anz/ijabbar/skins/anz_ijabbar/iJab.html
anz/ijabbar/skins/anz_ijabbar/ijab_config.js
anz/ijabbar/skins/anz_ijabbar/ijab_i18n_en.js
anz/ijabbar/skins/anz_ijabbar/ijab_i18n_zh.js
anz/ijabbar/skins/anz_ijabbar/ijab/0A9476898799A150D840F0B1C3672921.cache.png
anz/ijabbar/skins/anz_ijabbar/ijab/1ED2268B93EFBB45E571080A99A29BDD.cache.js
anz/ijabbar/skins/anz_ijabbar/ijab/209FA2DE4F10FB4071B1FA5DF791173C.cache.js
anz/ijabbar/skins/anz_ijabbar/ijab/396F806CD63ABD414BFBB9D57429F05B.cache.png
anz/ijabbar/skins/anz_ijabbar/ijab/5059281C97742B6D08C60DCFF6F9EE52.cache.js
anz/ijabbar/skins/anz_ijabbar/ijab/5D68E277095BEBB2A72B461684DF177E.cache.js
anz/ijabbar/skins/anz_ijabbar/ijab/676CC76F6640B3CEC9BAFAF22B0DF1DE.cache.js
anz/ijabbar/skins/anz_ijabbar/ijab/688FB6A1C7E3CB1FD38EC8EE0D995333.cache.js
anz/ijabbar/skins/anz_ijabbar/ijab/7CAD91010F4C656DCB88FB4D027D151F.cache.js
anz/ijabbar/skins/anz_ijabbar/ijab/81CD660C0945A5106B2B278D6F131761.cache.js
anz/ijabbar/skins/anz_ijabbar/ijab/82BE4E5464E770641C5338C99E8D976C.cache.js
anz/ijabbar/skins/anz_ijabbar/ijab/8603379B5088782D2C0620FAE856E112.cache.png
anz/ijabbar/skins/anz_ijabbar/ijab/87FAD0D2F14FDF271F4D01D8DE8359AC.cache.js
anz/ijabbar/skins/anz_ijabbar/ijab/92DC29E138A4D608D946BB6BC9A336B4.cache.js
anz/ijabbar/skins/anz_ijabbar/ijab/9331B89FB48FCD36F6C3D098C466AACA.cache.js
anz/ijabbar/skins/anz_ijabbar/ijab/98E75B990BFEBBAAF31BAE74363D3CF6.cache.js
anz/ijabbar/skins/anz_ijabbar/ijab/B05AE64AD60710809C3E8C7CF8659AA9.cache.js
anz/ijabbar/skins/anz_ijabbar/ijab/B4622E0E211B4B335FA22717FC668073.cache.js
anz/ijabbar/skins/anz_ijabbar/ijab/C8F595C72383C0FA198E17FFBCECFF25.cache.js
