Metadata-Version: 1.0
Name: anz.ijabbar
Version: 1.1
Summary: Integrate iJab(an open source XMPP web chat client recommended by xmpp.org) to your plone site.
Home-page: http://plone.org/products/anz.ijabbar/
Author: jiangdongjin
Author-email: eastxing@gmail.com
License: GPL
Keywords: plone xmpp web chat
Platform: UNKNOWN
Classifier: Framework :: Plone
Classifier: Programming Language :: Python
